mymorsecode/__init__.py
mymorsecode/audio.py
mymorsecode/morse.py
mymorsecode-0.5.0.dist-info/LICENSE
mymorsecode-0.5.0.dist-info/METADATA
mymorsecode-0.5.0.dist-info/WHEEL
mymorsecode-0.5.0.dist-info/RECORD
